blockutils/__init__.py
blockutils/_version.txt
blockutils/blocks.py
blockutils/common.py
blockutils/datapath.py
blockutils/e2e.py
blockutils/exceptions.py
blockutils/fetcher.py
blockutils/format.py
blockutils/geometry.py
blockutils/logging.py
blockutils/raster.py
blockutils/stac.py
blockutils/windows.py
blockutils/wmts.py
up42_blockutils-1.2.4.dist-info/METADATA
up42_blockutils-1.2.4.dist-info/WHEEL
up42_blockutils-1.2.4.dist-info/top_level.txt
up42_blockutils-1.2.4.dist-info/RECORD
