Metadata-Version: 2.1
Name: up42-blockutils
Version: 1.2.4
Summary: Block development toolkit for UP42
Home-page: https://www.up42.com
Author: UP42
Author-email: support@up42.com
License: MIT
Classifier: Programming Language :: Python :: 3
Classifier: License :: OSI Approved :: MIT License
Classifier: Operating System :: OS Independent
Classifier: Development Status :: 5 - Production/Stable
Classifier: Intended Audience :: Developers
Requires-Python: >=3.7, <3.10
Requires-Dist: area (==1.1.1)
Requires-Dist: ciso8601 (==2.2.0)
Requires-Dist: fiona (==1.8.20)
Requires-Dist: gcsfs (==2021.10.1)
Requires-Dist: geojson (==2.5.0)
Requires-Dist: geopandas (==0.10.2)
Requires-Dist: mercantile (==1.2.1)
Requires-Dist: packaging (==21.2)
Requires-Dist: pandas (<=1.3.4,>=1.2.0)
Requires-Dist: Pillow (==8.4.0)
Requires-Dist: pyproj (==3.2.1)
Requires-Dist: python-dateutil (==2.8.2)
Requires-Dist: rasterio (==1.2.2)
Requires-Dist: requests (==2.26.0)
Requires-Dist: rio-cogeo (==3.0.1)
Requires-Dist: scikit-image (==0.18.3)
Requires-Dist: shapely (==1.8.0)
Requires-Dist: xmltodict (==0.12.0)
